square/__init__.py
square/__main__.py
openseesboard-0.0.1.dist-info/METADATA
openseesboard-0.0.1.dist-info/WHEEL
openseesboard-0.0.1.dist-info/top_level.txt
openseesboard-0.0.1.dist-info/RECORD
